{"links":[{"source":0,"target":7},{"source":0,"target":39},{"source":0,"target":205},{"source":1,"target":182},{"source":1,"target":226},{"source":1,"target":227},{"source":1,"target":231},{"source":1,"target":232},{"source":1,"target":235},{"source":1,"target":250},{"source":1,"target":261},{"source":1,"target":289},{"source":1,"target":318},{"source":2,"target":178},{"source":2,"target":180},{"source":3,"target":198},{"source":3,"target":203},{"source":3,"target":204},{"source":3,"target":239},{"source":3,"target":294},{"source":3,"target":349},{"source":3,"target":387},{"source":4,"target":136},{"source":5,"target":155},{"source":5,"target":366},{"source":6,"target":385},{"source":7,"target":0},{"source":7,"target":292},{"source":8,"target":286},{"source":9,"target":235},{"source":9,"target":261},{"source":10,"target":56},{"source":10,"target":64},{"source":10,"target":79},{"source":10,"target":94},{"source":10,"target":162},{"source":10,"target":224},{"source":10,"target":329},{"source":10,"target":331},{"source":10,"target":334},{"source":10,"target":346},{"source":11,"target":31},{"source":13,"target":90},{"source":14,"target":30},{"source":15,"target":366},{"source":16,"target":12},{"source":16,"target":59},{"source":16,"target":150},{"source":16,"target":159},{"source":16,"target":166},{"source":16,"target":168},{"source":16,"target":177},{"source":16,"target":196},{"source":16,"target":250},{"source":18,"target":125},{"source":19,"target":185},{"source":20,"target":180},{"source":20,"target":285},{"source":20,"target":343},{"source":20,"target":391},{"source":22,"target":181},{"source":23,"target":154},{"source":23,"target":180},{"source":23,"target":251},{"source":23,"target":325},{"source":24,"target":100},{"source":25,"target":365},{"source":25,"target":365},{"source":26,"target":71},{"source":26,"target":180},{"source":26,"target":193},{"source":26,"target":218},{"source":26,"target":235},{"source":26,"target":257},{"source":26,"target":261},{"source":26,"target":274},{"source":26,"target":277},{"source":26,"target":286},{"source":26,"target":305},{"source":26,"target":308},{"source":26,"target":310},{"source":26,"target":317},{"source":26,"target":324},{"source":26,"target":350},{"source":27,"target":30},{"source":28,"target":150},{"source":29,"target":184},{"source":30,"target":14},{"source":30,"target":27},{"source":30,"target":203},{"source":30,"target":240},{"source":30,"target":370},{"source":31,"target":11},{"source":31,"target":172},{"source":31,"target":208},{"source":33,"target":36},{"source":33,"target":37},{"source":33,"target":64},{"source":34,"target":84},{"source":34,"target":229},{"source":34,"target":281},{"source":34,"target":389},{"source":36,"target":33},{"source":36,"target":37},{"source":36,"target":64},{"source":37,"target":33},{"source":37,"target":36},{"source":37,"target":64},{"source":39,"target":0},{"source":39,"target":52},{"source":39,"target":78},{"source":39,"target":90},{"source":39,"target":94},{"source":39,"target":135},{"source":39,"target":150},{"source":39,"target":190},{"source":39,"target":279},{"source":39,"target":286},{"source":39,"target":293},{"source":39,"target":296},{"source":39,"target":366},{"source":39,"target":371},{"source":39,"target":394},{"source":41,"target":203},{"source":41,"target":262},{"source":41,"target":303},{"source":41,"target":342},{"source":44,"target":184},{"source":45,"target":248},{"source":47,"target":307},{"source":49,"target":288},{"source":50,"target":118},{"source":50,"target":180},{"source":50,"target":252},{"source":51,"target":306},{"source":52,"target":39},{"source":53,"target":181},{"source":53,"target":358},{"source":54,"target":174},{"source":54,"target":194},{"source":54,"target":199},{"source":54,"target":368},{"source":54,"target":375},{"source":55,"target":73},{"source":56,"target":10},{"source":57,"target":86},{"source":57,"target":235},{"source":57,"target":257},{"source":57,"target":261},{"source":57,"target":315},{"source":58,"target":120},{"source":58,"target":180},{"source":58,"target":292},{"source":59,"target":12},{"source":59,"target":16},{"source":59,"target":150},{"source":59,"target":179},{"source":59,"target":196},{"source":59,"target":345},{"source":60,"target":137},{"source":62,"target":32},{"source":62,"target":250},{"source":62,"target":297},{"source":62,"target":333},{"source":63,"target":118},{"source":63,"target":180},{"source":63,"target":259},{"source":64,"target":10},{"source":64,"target":33},{"source":64,"target":36},{"source":64,"target":37},{"source":65,"target":111},{"source":65,"target":203},{"source":65,"target":285},{"source":67,"target":150},{"source":67,"target":235},{"source":67,"target":261},{"source":67,"target":354},{"source":67,"target":383},{"source":69,"target":107},{"source":70,"target":246},{"source":71,"target":26},{"source":72,"target":150},{"source":73,"target":55},{"source":73,"target":191},{"source":73,"target":348},{"source":73,"target":363},{"source":74,"target":204},{"source":78,"target":39},{"source":78,"target":253},{"source":78,"target":290},{"source":79,"target":10},{"source":79,"target":334},{"source":79,"target":390},{"source":80,"target":106},{"source":81,"target":203},{"source":81,"target":215},{"source":83,"target":181},{"source":83,"target":390},{"source":85,"target":141},{"source":85,"target":180},{"source":85,"target":292},{"source":86,"target":57},{"source":87,"target":48},{"source":87,"target":98},{"source":87,"target":203},{"source":87,"target":204},{"source":87,"target":250},{"source":87,"target":262},{"source":87,"target":303},{"source":87,"target":307},{"source":87,"target":342},{"source":87,"target":389},{"source":88,"target":48},{"source":88,"target":301},{"source":88,"target":381},{"source":89,"target":266},{"source":90,"target":13},{"source":90,"target":39},{"source":91,"target":287},{"source":92,"target":388},{"source":94,"target":10},{"source":94,"target":39},{"source":95,"target":363},{"source":98,"target":87},{"source":98,"target":201},{"source":98,"target":343},{"source":99,"target":183},{"source":100,"target":24},{"source":103,"target":224},{"source":103,"target":242},{"source":103,"target":243},{"source":103,"target":244},{"source":103,"target":245},{"source":103,"target":248},{"source":103,"target":250},{"source":103,"target":264},{"source":103,"target":265},{"source":103,"target":271},{"source":103,"target":272},{"source":103,"target":273},{"source":103,"target":329},{"source":104,"target":135},{"source":105,"target":108},{"source":106,"target":80},{"source":107,"target":69},{"source":107,"target":75},{"source":107,"target":77},{"source":107,"target":150},{"source":107,"target":300},{"source":107,"target":359},{"source":108,"target":105},{"source":108,"target":330},{"source":111,"target":65},{"source":112,"target":131},{"source":114,"target":386},{"source":116,"target":76},{"source":117,"target":270},{"source":118,"target":50},{"source":118,"target":63},{"source":118,"target":194},{"source":118,"target":195},{"source":118,"target":197},{"source":118,"target":233},{"source":119,"target":93},{"source":119,"target":161},{"source":119,"target":220},{"source":119,"target":249},{"source":120,"target":58},{"source":121,"target":105},{"source":123,"target":96},{"source":123,"target":336},{"source":123,"target":361},{"source":124,"target":150},{"source":124,"target":254},{"source":124,"target":254},{"source":126,"target":366},{"source":128,"target":160},{"source":129,"target":154},{"source":131,"target":112},{"source":131,"target":268},{"source":133,"target":203},{"source":134,"target":40},{"source":135,"target":39},{"source":135,"target":104},{"source":135,"target":291},{"source":137,"target":60},{"source":138,"target":304},{"source":138,"target":329},{"source":138,"target":384},{"source":138,"target":384},{"source":139,"target":380},{"source":140,"target":347},{"source":141,"target":85},{"source":142,"target":180},{"source":142,"target":184},{"source":142,"target":246},{"source":143,"target":241},{"source":145,"target":286},{"source":145,"target":326},{"source":148,"target":148},{"source":148,"target":148},{"source":148,"target":203},{"source":148,"target":357},{"source":150,"target":16},{"source":150,"target":21},{"source":150,"target":28},{"source":150,"target":39},{"source":150,"target":59},{"source":150,"target":67},{"source":150,"target":72},{"source":150,"target":107},{"source":150,"target":124},{"source":150,"target":185},{"source":150,"target":203},{"source":150,"target":248},{"source":150,"target":250},{"source":150,"target":329},{"source":151,"target":213},{"source":152,"target":61},{"source":153,"target":202},{"source":154,"target":23},{"source":155,"target":5},{"source":156,"target":352},{"source":157,"target":201},{"source":158,"target":309},{"source":159,"target":16},{"source":160,"target":360},{"source":161,"target":119},{"source":162,"target":10},{"source":162,"target":351},{"source":163,"target":222},{"source":164,"target":222},{"source":165,"target":214},{"source":166,"target":16},{"source":168,"target":16},{"source":168,"target":184},{"source":172,"target":31},{"source":172,"target":180},{"source":172,"target":200},{"source":174,"target":54},{"source":176,"target":293},{"source":176,"target":372},{"source":177,"target":16},{"source":177,"target":185},{"source":177,"target":359},{"source":178,"target":2},{"source":179,"target":59},{"source":179,"target":309},{"source":180,"target":2},{"source":180,"target":20},{"source":180,"target":23},{"source":180,"target":26},{"source":180,"target":50},{"source":180,"target":58},{"source":180,"target":63},{"source":180,"target":85},{"source":180,"target":142},{"source":180,"target":172},{"source":180,"target":184},{"source":180,"target":208},{"source":180,"target":238},{"source":180,"target":251},{"source":180,"target":275},{"source":180,"target":348},{"source":180,"target":363},{"source":180,"target":372},{"source":184,"target":29},{"source":184,"target":44},{"source":184,"target":142},{"source":184,"target":168},{"source":184,"target":180},{"source":184,"target":195},{"source":184,"target":203},{"source":184,"target":240},{"source":184,"target":271},{"source":184,"target":275},{"source":184,"target":284},{"source":184,"target":360},{"source":184,"target":366},{"source":185,"target":19},{"source":185,"target":150},{"source":185,"target":177},{"source":185,"target":186},{"source":185,"target":216},{"source":185,"target":217},{"source":185,"target":218},{"source":185,"target":219},{"source":185,"target":250},{"source":185,"target":257},{"source":185,"target":258},{"source":185,"target":260},{"source":185,"target":263},{"source":185,"target":274},{"source":185,"target":277},{"source":185,"target":296},{"source":185,"target":298},{"source":185,"target":356},{"source":185,"target":371},{"source":186,"target":185},{"source":186,"target":222},{"source":186,"target":351},{"source":187,"target":222},{"source":188,"target":351},{"source":189,"target":222},{"source":190,"target":39},{"source":191,"target":73},{"source":191,"target":222},{"source":191,"target":375},{"source":192,"target":222},{"source":192,"target":298},{"source":193,"target":26},{"source":193,"target":222},{"source":194,"target":54},{"source":194,"target":118},{"source":195,"target":118},{"source":195,"target":184},{"source":195,"target":222},{"source":197,"target":118},{"source":197,"target":222},{"source":198,"target":3},{"source":200,"target":172},{"source":201,"target":98},{"source":201,"target":157},{"source":201,"target":285},{"source":201,"target":343},{"source":202,"target":153},{"source":202,"target":267},{"source":203,"target":3},{"source":203,"target":30},{"source":203,"target":41},{"source":203,"target":65},{"source":203,"target":81},{"source":203,"target":87},{"source":203,"target":133},{"source":203,"target":148},{"source":203,"target":150},{"source":203,"target":184},{"source":203,"target":206},{"source":203,"target":214},{"source":203,"target":241},{"source":203,"target":269},{"source":203,"target":301},{"source":203,"target":303},{"source":203,"target":352},{"source":203,"target":365},{"source":204,"target":3},{"source":204,"target":74},{"source":204,"target":87},{"source":204,"target":294},{"source":204,"target":311},{"source":204,"target":313},{"source":204,"target":316},{"source":204,"target":323},{"source":204,"target":349},{"source":204,"target":387},{"source":205,"target":0},{"source":205,"target":292},{"source":206,"target":203},{"source":206,"target":362},{"source":207,"target":330},{"source":208,"target":31},{"source":208,"target":180},{"source":208,"target":221},{"source":209,"target":330},{"source":210,"target":330},{"source":211,"target":330},{"source":212,"target":330},{"source":213,"target":238},{"source":214,"target":165},{"source":214,"target":203},{"source":214,"target":294},{"source":215,"target":81},{"source":216,"target":185},{"source":216,"target":298},{"source":217,"target":185},{"source":218,"target":26},{"source":218,"target":185},{"source":219,"target":185},{"source":219,"target":356},{"source":221,"target":208},{"source":222,"target":38},{"source":222,"target":163},{"source":222,"target":164},{"source":222,"target":186},{"source":222,"target":187},{"source":222,"target":189},{"source":222,"target":191},{"source":222,"target":192},{"source":222,"target":193},{"source":222,"target":195},{"source":222,"target":197},{"source":222,"target":250},{"source":222,"target":310},{"source":222,"target":353},{"source":222,"target":375},{"source":222,"target":384},{"source":222,"target":384},{"source":223,"target":393},{"source":224,"target":10},{"source":224,"target":103},{"source":224,"target":359},{"source":225,"target":359},{"source":226,"target":1},{"source":227,"target":1},{"source":228,"target":359},{"source":228,"target":372},{"source":230,"target":330},{"source":231,"target":1},{"source":232,"target":1},{"source":233,"target":118},{"source":235,"target":1},{"source":235,"target":9},{"source":235,"target":26},{"source":235,"target":57},{"source":235,"target":67},{"source":235,"target":261},{"source":235,"target":367},{"source":237,"target":348},{"source":238,"target":180},{"source":238,"target":213},{"source":238,"target":251},{"source":238,"target":325},{"source":239,"target":3},{"source":240,"target":30},{"source":240,"target":184},{"source":241,"target":143},{"source":241,"target":203},{"source":242,"target":103},{"source":243,"target":103},{"source":244,"target":103},{"source":244,"target":372},{"source":245,"target":103},{"source":246,"target":142},{"source":247,"target":251},{"source":248,"target":45},{"source":248,"target":103},{"source":248,"target":150},{"source":249,"target":93},{"source":249,"target":119},{"source":249,"target":220},{"source":249,"target":250},{"source":249,"target":312},{"source":249,"target":322},{"source":249,"target":324},{"source":249,"target":384},{"source":249,"target":384},{"source":250,"target":1},{"source":250,"target":16},{"source":250,"target":21},{"source":250,"target":62},{"source":250,"target":87},{"source":250,"target":103},{"source":250,"target":150},{"source":250,"target":185},{"source":250,"target":222},{"source":250,"target":249},{"source":250,"target":278},{"source":250,"target":320},{"source":250,"target":329},{"source":250,"target":332},{"source":250,"target":351},{"source":250,"target":359},{"source":251,"target":23},{"source":251,"target":180},{"source":251,"target":238},{"source":251,"target":247},{"source":251,"target":313},{"source":251,"target":314},{"source":251,"target":319},{"source":251,"target":321},{"source":251,"target":323},{"source":251,"target":325},{"source":251,"target":369},{"source":251,"target":387},{"source":252,"target":50},{"source":253,"target":78},{"source":254,"target":124},{"source":254,"target":124},{"source":255,"target":394},{"source":256,"target":372},{"source":257,"target":26},{"source":257,"target":57},{"source":257,"target":185},{"source":258,"target":185},{"source":258,"target":355},{"source":258,"target":372},{"source":259,"target":63},{"source":260,"target":185},{"source":261,"target":1},{"source":261,"target":9},{"source":261,"target":26},{"source":261,"target":57},{"source":261,"target":67},{"source":261,"target":235},{"source":262,"target":41},{"source":262,"target":87},{"source":263,"target":185},{"source":264,"target":103},{"source":265,"target":103},{"source":265,"target":292},{"source":267,"target":202},{"source":268,"target":131},{"source":269,"target":203},{"source":270,"target":117},{"source":271,"target":103},{"source":271,"target":184},{"source":272,"target":103},{"source":273,"target":103},{"source":273,"target":292},{"source":274,"target":26},{"source":274,"target":185},{"source":274,"target":286},{"source":274,"target":309},{"source":275,"target":180},{"source":275,"target":184},{"source":275,"target":287},{"source":277,"target":26},{"source":277,"target":185},{"source":277,"target":298},{"source":278,"target":250},{"source":279,"target":39},{"source":279,"target":309},{"source":281,"target":34},{"source":281,"target":389},{"source":284,"target":184},{"source":285,"target":20},{"source":285,"target":65},{"source":285,"target":201},{"source":286,"target":8},{"source":286,"target":26},{"source":286,"target":39},{"source":286,"target":145},{"source":286,"target":274},{"source":286,"target":295},{"source":286,"target":328},{"source":286,"target":350},{"source":287,"target":275},{"source":288,"target":49},{"source":289,"target":1},{"source":289,"target":359},{"source":290,"target":78},{"source":291,"target":135},{"source":292,"target":7},{"source":292,"target":58},{"source":292,"target":85},{"source":292,"target":205},{"source":292,"target":265},{"source":292,"target":273},{"source":292,"target":379},{"source":293,"target":39},{"source":293,"target":109},{"source":293,"target":146},{"source":293,"target":176},{"source":293,"target":372},{"source":294,"target":3},{"source":294,"target":204},{"source":294,"target":214},{"source":294,"target":372},{"source":297,"target":32},{"source":297,"target":62},{"source":297,"target":333},{"source":297,"target":377},{"source":298,"target":185},{"source":298,"target":192},{"source":298,"target":216},{"source":298,"target":277},{"source":300,"target":107},{"source":300,"target":309},{"source":301,"target":88},{"source":301,"target":203},{"source":301,"target":309},{"source":302,"target":330},{"source":303,"target":41},{"source":303,"target":87},{"source":303,"target":203},{"source":304,"target":138},{"source":304,"target":309},{"source":304,"target":351},{"source":304,"target":374},{"source":304,"target":384},{"source":305,"target":26},{"source":305,"target":309},{"source":305,"target":351},{"source":305,"target":374},{"source":306,"target":331},{"source":307,"target":46},{"source":307,"target":47},{"source":307,"target":87},{"source":307,"target":115},{"source":307,"target":365},{"source":307,"target":365},{"source":307,"target":369},{"source":307,"target":373},{"source":308,"target":26},{"source":308,"target":351},{"source":309,"target":158},{"source":309,"target":179},{"source":309,"target":274},{"source":309,"target":279},{"source":309,"target":300},{"source":309,"target":301},{"source":309,"target":304},{"source":309,"target":305},{"source":310,"target":26},{"source":310,"target":222},{"source":311,"target":204},{"source":312,"target":249},{"source":313,"target":204},{"source":313,"target":251},{"source":314,"target":251},{"source":315,"target":57},{"source":315,"target":351},{"source":316,"target":204},{"source":317,"target":26},{"source":317,"target":351},{"source":318,"target":1},{"source":319,"target":251},{"source":320,"target":250},{"source":321,"target":251},{"source":322,"target":249},{"source":323,"target":204},{"source":323,"target":251},{"source":324,"target":26},{"source":324,"target":249},{"source":325,"target":23},{"source":325,"target":238},{"source":325,"target":251},{"source":326,"target":145},{"source":328,"target":286},{"source":329,"target":10},{"source":329,"target":103},{"source":329,"target":138},{"source":329,"target":150},{"source":329,"target":250},{"source":329,"target":359},{"source":330,"target":17},{"source":330,"target":108},{"source":330,"target":132},{"source":330,"target":207},{"source":330,"target":209},{"source":330,"target":210},{"source":330,"target":211},{"source":330,"target":212},{"source":330,"target":230},{"source":330,"target":302},{"source":330,"target":335},{"source":330,"target":375},{"source":331,"target":10},{"source":331,"target":306},{"source":331,"target":334},{"source":332,"target":250},{"source":333,"target":62},{"source":333,"target":297},{"source":334,"target":10},{"source":334,"target":79},{"source":334,"target":331},{"source":335,"target":330},{"source":336,"target":123},{"source":337,"target":9},{"source":338,"target":376},{"source":339,"target":382},{"source":340,"target":372},{"source":341,"target":360},{"source":342,"target":41},{"source":342,"target":87},{"source":343,"target":20},{"source":343,"target":98},{"source":343,"target":201},{"source":345,"target":59},{"source":346,"target":10},{"source":346,"target":385},{"source":347,"target":140},{"source":348,"target":73},{"source":348,"target":180},{"source":348,"target":237},{"source":351,"target":110},{"source":351,"target":162},{"source":351,"target":186},{"source":351,"target":188},{"source":351,"target":250},{"source":351,"target":304},{"source":351,"target":305},{"source":351,"target":308},{"source":351,"target":315},{"source":351,"target":317},{"source":351,"target":364},{"source":351,"target":374},{"source":351,"target":384},{"source":351,"target":384},{"source":352,"target":156},{"source":352,"target":203},{"source":355,"target":258},{"source":356,"target":185},{"source":356,"target":219},{"source":357,"target":148},{"source":359,"target":75},{"source":359,"target":77},{"source":359,"target":107},{"source":359,"target":177},{"source":359,"target":224},{"source":359,"target":225},{"source":359,"target":228},{"source":359,"target":250},{"source":359,"target":289},{"source":359,"target":329},{"source":360,"target":160},{"source":360,"target":184},{"source":360,"target":341},{"source":362,"target":206},{"source":363,"target":73},{"source":363,"target":95},{"source":363,"target":180},{"source":365,"target":25},{"source":365,"target":25},{"source":365,"target":46},{"source":365,"target":115},{"source":365,"target":203},{"source":365,"target":307},{"source":365,"target":307},{"source":365,"target":369},{"source":365,"target":373},{"source":366,"target":5},{"source":366,"target":15},{"source":366,"target":39},{"source":366,"target":97},{"source":366,"target":126},{"source":366,"target":184},{"source":366,"target":376},{"source":367,"target":182},{"source":367,"target":235},{"source":369,"target":251},{"source":369,"target":307},{"source":369,"target":365},{"source":372,"target":146},{"source":372,"target":176},{"source":372,"target":180},{"source":372,"target":228},{"source":372,"target":244},{"source":372,"target":256},{"source":372,"target":258},{"source":372,"target":293},{"source":372,"target":294},{"source":372,"target":340},{"source":374,"target":110},{"source":374,"target":304},{"source":374,"target":305},{"source":374,"target":351},{"source":374,"target":364},{"source":375,"target":38},{"source":375,"target":54},{"source":375,"target":191},{"source":375,"target":222},{"source":375,"target":330},{"source":375,"target":353},{"source":376,"target":338},{"source":376,"target":366},{"source":379,"target":292},{"source":380,"target":139},{"source":382,"target":339},{"source":383,"target":67},{"source":384,"target":138},{"source":384,"target":138},{"source":384,"target":222},{"source":384,"target":222},{"source":384,"target":249},{"source":384,"target":249},{"source":384,"target":304},{"source":384,"target":351},{"source":384,"target":351},{"source":385,"target":6},{"source":385,"target":346},{"source":386,"target":114},{"source":387,"target":3},{"source":387,"target":204},{"source":387,"target":251},{"source":389,"target":34},{"source":389,"target":84},{"source":389,"target":87},{"source":389,"target":281},{"source":390,"target":79},{"source":391,"target":20},{"source":393,"target":223},{"source":394,"target":39},{"source":394,"target":255}],"nodes":[{"group":"E22_ManMadeObject","name":"e22_long_table_1"},{"group":"E22_ManMadeObject","name":"e22_porch"},{"group":"E21_Person","name":"e21_willian_barlow"},{"group":"E53_Place","name":"e53_great_hall"},{"group":"E61_TimePrimitive","name":"e61_1824-1845"},{"group":"E21_Person","name":"e21_peter_price"},{"group":"E44_PlaceAppellation","name":"e44_deer_park"},{"group":"E12_Production","name":"e12_long_table_1"},{"group":"E63_BeginningOfExistence","name":"e63_portrait_bishop_bagot"},{"group":"E52_TimeSpan","name":"e52_1845-1854"},{"group":"E21_Person","name":"e21_jocelin_trotman"},{"group":"E82_ActorAppellation","name":"e82_ken_thomas"},{"group":"E73_InformationObject","name":"\/data.bishopspalace.org.uk\/staircase.html"},{"group":"E46_SectionDefinition","name":"e46_long_gallery_east"},{"group":"E44_PlaceAppellation","name":"e44_beckynton_range"},{"group":"E63_BeginningOfExistence","name":"e63_portrait_price"},{"group":"E22_ManMadeObject","name":"e22_staircase_medieval"},{"group":"E42_Identifier","name":"\/data.bishopspalace.org.uk\/glastonbury_chair"},{"group":"E61_TimePrimitive","name":"e61_1824-1829"},{"group":"E41_Appellation","name":"e41_beckynton_range"},{"group":"E21_Person","name":"e21_ralph_of_shrewsbury"},{"group":"E42_Identifier","name":"\/data.bishopspalace.org.uk\/jocelins_palace"},{"group":"E61_TimePrimitive","name":"e61_1206-1242"},{"group":"E86_Leaving","name":"e86_burnell"},{"group":"E44_PlaceAppellation","name":"e44_garden_of_reflection"},{"group":"E44_PlaceAppellation","name":"e44_bishops_chapel"},{"group":"E21_Person","name":"e21_richard_bagot"},{"group":"E47_SpatialCoordinates","name":"e47_geo_1"},{"group":"E47_SpatialCoordinates","name":"e47_geo_2"},{"group":"E38_Image","name":"e38_portrait_bishop_backynton"},{"group":"E53_Place","name":"e53_beckynton_range"},{"group":"E21_Person","name":"e21_ken_thomas"},{"group":"E42_Identifier","name":"\/data.bishopspalace.org.uk\/east_gallery"},{"group":"E82_ActorAppellation","name":"e82_jocelin_3"},{"group":"E53_Place","name":"e53_croquet_lawn"},{"group":"E82_ActorAppellation","name":"e82_bishop_of_wells"},{"group":"E82_ActorAppellation","name":"e82_jocelin_1"},{"group":"E82_ActorAppellation","name":"e82_jocelin_2"},{"group":"E73_InformationObject","name":"\/data.bishopspalace.org.uk\/drawing_room.html"},{"group":"E53_Place","name":"e53_long_gallery"},{"group":"E52_TimeSpan","name":"e52_1275-1292"},{"group":"E22_ManMadeObject","name":"e22_bishops_palace"},{"group":"E55_Type","name":"e55_e22_furniture"},{"group":"E44_PlaceAppellation","name":"e44_conference_room"},{"group":"E82_ActorAppellation","name":"e82_thomas_beckynton"},{"group":"E44_PlaceAppellation","name":"e44_undercroft"},{"group":"E73_InformationObject","name":"\/data.bishopspalace.org.uk\/audio\/choral.mp3"},{"group":"E41_Appellation","name":"e41_chapel"},{"group":"E42_Identifier","name":"\/data.bishopspalace.org.uk\/croquet_lawn#west"},{"group":"E44_PlaceAppellation","name":"e44_outer_gardens"},{"group":"E86_Leaving","name":"e86_bradfield"},{"group":"E61_TimePrimitive","name":"e61_1206"},{"group":"E47_SpatialCoordinates","name":"geo:1,1,1;crs=geo.bishopspalace.org.uk;u=2"},{"group":"E61_TimePrimitive","name":"e61_1200"},{"group":"E22_ManMadeObject","name":"e22_coronation_cope"},{"group":"E82_ActorAppellation","name":"e82_piers_william"},{"group":"E38_Image","name":"e38_portrait_bshop_jocelin"},{"group":"E21_Person","name":"e21_ferrey_benjamin"},{"group":"E85_Joining","name":"e85_hervey"},{"group":"E53_Place","name":"e53_staircase"},{"group":"E82_ActorAppellation","name":"e82_king_john"},{"group":"E52_TimeSpan","name":"e52_1548-1553"},{"group":"E22_ManMadeObject","name":"e22_east_gallery"},{"group":"E85_Joining","name":"e85_bradfield"},{"group":"E82_ActorAppellation","name":"e82_jocelin_trotman"},{"group":"E53_Place","name":"e53_ramparts"},{"group":"E55_Type","name":"e55_e22_building"},{"group":"E53_Place","name":"e53_entrance_porch"},{"group":"E55_Type","name":"e55_notes_children"},{"group":"E44_PlaceAppellation","name":"e44_entrance_hall"},{"group":"E61_TimePrimitive","name":"e61_1465"},{"group":"E82_ActorAppellation","name":"e82_richard_bagot"},{"group":"E44_PlaceAppellation","name":"e44_jocelins_palace"},{"group":"E21_Person","name":"e21_piers_william"},{"group":"E41_Appellation","name":"e41_great_hall"},{"group":"E42_Identifier","name":"\/data.bishopspalace.org.uk\/entrance_hall"},{"group":"E52_TimeSpan","name":"e52_1443-1465"},{"group":"E73_InformationObject","name":"\/data.bishopspalace.org.uk\/entrance_hall.html"},{"group":"E53_Place","name":"e53_long_gallery_north"},{"group":"E86_Leaving","name":"e86_jocelin"},{"group":"E44_PlaceAppellation","name":"e44_gatehouse"},{"group":"E53_Place","name":"e53_bishop_laws_grotto"},{"group":"E41_Appellation","name":"e41_long_gallery"},{"group":"E61_TimePrimitive","name":"e61_1242"},{"group":"E42_Identifier","name":"\/data.bishopspalace.org.uk\/croquet_lawn#south"},{"group":"E86_Leaving","name":"e86_hervey"},{"group":"E82_ActorAppellation","name":"e82_benjamin_ferey"},{"group":"E27_Site","name":"e27_bishops_palace"},{"group":"E53_Place","name":"e53_visitor_entrance_gate"},{"group":"E61_TimePrimitive","name":"e61_1450"},{"group":"E53_Place","name":"e53_long_gallery_east"},{"group":"E61_TimePrimitive","name":"e61_1443"},{"group":"E61_TimePrimitive","name":"e61_1239"},{"group":"E73_InformationObject","name":"\/data.bishopspalace.org.uk\/panelled_room.html"},{"group":"E63_BeginningOfExistence","name":"e63_long_Gallery"},{"group":"E52_TimeSpan","name":"e52_1632"},{"group":"E42_Identifier","name":"\/data.bishopspalace.org.uk\/welcome_to_the_bishops_palace"},{"group":"E42_Identifier","name":"\/data.bishopspalace.org.uk\/portrait_bishop_price_01"},{"group":"E25_ManMadeFeature","name":"e25_moat"},{"group":"E61_TimePrimitive","name":"e61_1329-1363"},{"group":"E53_Place","name":"e53_garden_of_reflection"},{"group":"E44_PlaceAppellation","name":"e44_panelled_room"},{"group":"E55_Type","name":"e55_notes_detailed"},{"group":"E22_ManMadeObject","name":"e22_undercroft"},{"group":"E46_SectionDefinition","name":"e46_long_gallery_south"},{"group":"E52_TimeSpan","name":"e52_1500"},{"group":"E53_Place","name":"e53_gatehouse"},{"group":"E53_Place","name":"e53_entrance_hall"},{"group":"E12_Production","name":"e12_glastonbury_chair"},{"group":"E42_Identifier","name":"\/data.bishopspalace.org.uk\/portrait_bishop_law_01"},{"group":"E42_Identifier","name":"\/data.bishopspalace.org.uk\/conference_room"},{"group":"E44_PlaceAppellation","name":"e44_ramparts"},{"group":"E44_PlaceAppellation","name":"e44_wells_cathedral"},{"group":"E55_Type","name":"e55_notes_pilot"},{"group":"E44_PlaceAppellation","name":"e44_market_place_water_fountain"},{"group":"E73_InformationObject","name":"\/data.bishopspalace.org.uk\/bishops_chapel.html"},{"group":"E61_TimePrimitive","name":"e61_1443-1465"},{"group":"E44_PlaceAppellation","name":"e44_phelps_garden"},{"group":"E21_Person","name":"e21_bradfield_harold"},{"group":"E53_Place","name":"e53_panelled_room"},{"group":"E52_TimeSpan","name":"e52_1869"},{"group":"E61_TimePrimitive","name":"e61_1500"},{"group":"E42_Identifier","name":"\/data.bishopspalace.org.uk\/portrait_bishop_jocelin_01"},{"group":"E28_ConceptualObject","name":"e28_tour"},{"group":"E53_Place","name":"e53_great_chamber"},{"group":"E52_TimeSpan","name":"e52_1824-1829"},{"group":"E41_Appellation","name":"e41_portrait_price"},{"group":"E55_Type","name":"e55_notes_garden_tour"},{"group":"E61_TimePrimitive","name":"e61_1390"},{"group":"E61_TimePrimitive","name":"e61_1292"},{"group":"E44_PlaceAppellation","name":"e44_drawing_room"},{"group":"E53_Place","name":"e53_wells_cathedral"},{"group":"E73_InformationObject","name":"\/data.bishopspalace.org.uk\/glastonbury_chair.html"},{"group":"E45_Address","name":"e45_bishops_palace"},{"group":"E61_TimePrimitive","name":"e61_1275-1292"},{"group":"E53_Place","name":"e53_long_gallery_south"},{"group":"E52_TimeSpan","name":"e52_1824-1845"},{"group":"E21_Person","name":"e21_king_john"},{"group":"E22_ManMadeObject","name":"e22_jocelins_great_hall"},{"group":"E21_Person","name":"e21_king_edward_sixth"},{"group":"E67_Birth","name":"e67_birth_burnell"},{"group":"E52_TimeSpan","name":"e52_1894"},{"group":"E86_Leaving","name":"e86_beckynton"},{"group":"E44_PlaceAppellation","name":"e44_well_house"},{"group":"E44_PlaceAppellation","name":"e44_croquet_lawn"},{"group":"E38_Image","name":"e38_portrait_bishop_bagot_01"},{"group":"E73_InformationObject","name":"\/data.bishopspalace.org.uk\/bishop_law.html"},{"group":"E55_Type","name":"e55_role_architect"},{"group":"E53_Place","name":"e53_well_pool"},{"group":"E55_Type","name":"e55_notes_architecture"},{"group":"E53_Place","name":"e53_jocelins_palace"},{"group":"E61_TimePrimitive","name":"e61_1275"},{"group":"E61_TimePrimitive","name":"e61_1548-1553"},{"group":"E07_Activity","name":"e07_painting_portrait_price"},{"group":"E52_TimeSpan","name":"e52_1292"},{"group":"E82_ActorAppellation","name":"e82_peter_price"},{"group":"E44_PlaceAppellation","name":"e44_aboretum"},{"group":"E44_PlaceAppellation","name":"e44_moat"},{"group":"E62_String","name":"tour\/e62_038"},{"group":"E62_String","name":"e62_086"},{"group":"E52_TimeSpan","name":"e52_1390"},{"group":"E62_String","name":"tour\/e62_039"},{"group":"E62_String","name":"e62_087"},{"group":"E62_String","name":"e62_088"},{"group":"E62_String","name":"e62_089"},{"group":"E44_PlaceAppellation","name":"e44_south_lawn"},{"group":"E62_String","name":"e62_083"},{"group":"E62_String","name":"tour\/e62_045"},{"group":"E62_String","name":"e62_082"},{"group":"E62_String","name":"e62_085"},{"group":"E62_String","name":"e62_084"},{"group":"E62_String","name":"tour\/e62_042"},{"group":"E86_Leaving","name":"e86_ken"},{"group":"E62_String","name":"tour\/e62_041"},{"group":"E62_String","name":"tour\/e62_044"},{"group":"E62_String","name":"e62_081"},{"group":"E62_String","name":"tour\/e62_043"},{"group":"E62_String","name":"e62_080"},{"group":"E82_ActorAppellation","name":"e82_william_barlow"},{"group":"E62_String","name":"tour\/e62_040"},{"group":"E74_Group","name":"e74_bishop_bath_wells"},{"group":"E52_TimeSpan","name":"e52_1206-1242"},{"group":"E42_Identifier","name":"\/data.bishopspalace.org.uk\/croquet_lawn#east"},{"group":"E52_TimeSpan","name":"e52_1329-1363"},{"group":"E21_Person","name":"e21_thomas_beckynton"},{"group":"E22_ManMadeObject","name":"e22_long_gallery"},{"group":"E62_String","name":"e62_099"},{"group":"E62_String","name":"e62_097"},{"group":"E62_String","name":"e62_098"},{"group":"E62_String","name":"e62_096"},{"group":"E44_PlaceAppellation","name":"e44_long_gallery"},{"group":"E62_String","name":"e62_095"},{"group":"E62_String","name":"e62_094"},{"group":"E62_String","name":"e62_093"},{"group":"E62_String","name":"e62_092"},{"group":"E62_String","name":"e62_091"},{"group":"E42_Identifier","name":"\/data.bishopspalace.org.uk\/staircase"},{"group":"E62_String","name":"e62_090"},{"group":"E44_PlaceAppellation","name":"e44_great_hall"},{"group":"E73_InformationObject","name":"\/data.bishopspalace.org.uk\/coronation_cope.html"},{"group":"E52_TimeSpan","name":"e52_1691"},{"group":"E53_Place","name":"e53_moat"},{"group":"E55_Type","name":"e55_oil_painting"},{"group":"E53_Place","name":"e53_bishops_palace"},{"group":"E22_ManMadeObject","name":"e22_burnells_great_hall"},{"group":"E62_String","name":"e62_064"},{"group":"E53_Place","name":"e53_victorian_garden"},{"group":"E62_String","name":"e62_065"},{"group":"E85_Joining","name":"e85_ken"},{"group":"E62_String","name":"e62_066"},{"group":"E62_String","name":"e62_067"},{"group":"E62_String","name":"e62_068"},{"group":"E62_String","name":"e62_069"},{"group":"E52_TimeSpan","name":"e52_1275"},{"group":"E53_Place","name":"e53_south_lawn"},{"group":"E44_PlaceAppellation","name":"e44_bishop_laws_grotto"},{"group":"E62_String","name":"e62_061"},{"group":"E62_String","name":"e62_060"},{"group":"E62_String","name":"e62_063"},{"group":"E62_String","name":"e62_062"},{"group":"E42_Identifier","name":"\/data.bishopspalace.org.uk\/panelled_room"},{"group":"E52_TimeSpan","name":"e52_1685"},{"group":"E22_ManMadeObject","name":"e22_drawing_room"},{"group":"E82_ActorAppellation","name":"e82_king_henry_third"},{"group":"E62_String","name":"e62_077"},{"group":"E62_String","name":"e62_078"},{"group":"E62_String","name":"e62_075"},{"group":"E62_String","name":"e62_076"},{"group":"E62_String","name":"e62_079"},{"group":"E73_InformationObject","name":"\/data.bishopspalace.org.uk\/croquet_lawn_south.html"},{"group":"E62_String","name":"e62_070"},{"group":"E62_String","name":"e62_074"},{"group":"E62_String","name":"e62_073"},{"group":"E82_ActorAppellation","name":"e82_bradfield_harold"},{"group":"E62_String","name":"e62_072"},{"group":"E62_String","name":"e62_071"},{"group":"E55_Type","name":"e55_role_purchaser"},{"group":"E52_TimeSpan","name":"e52_1670"},{"group":"E85_Joining","name":"e85_burnell"},{"group":"E47_SpatialCoordinates","name":"geo:2.2,-2.2;crs=geo.bishopspalace.org.uk;u=2"},{"group":"E12_Production","name":"e12_beckynton_range"},{"group":"E53_Place","name":"e53_well_house"},{"group":"E62_String","name":"e62_047"},{"group":"E62_String","name":"e62_046"},{"group":"E62_String","name":"e62_049"},{"group":"E62_String","name":"e62_048"},{"group":"E52_TimeSpan","name":"e52_1465"},{"group":"E82_ActorAppellation","name":"e82_robert_burnell"},{"group":"E53_Place","name":"e53_undercroft"},{"group":"E22_ManMadeObject","name":"e22_panelled_room"},{"group":"E22_ManMadeObject","name":"e22_jocelins_palace"},{"group":"E21_Person","name":"e21_robert_burnell"},{"group":"E52_TimeSpan","name":"e52_1960"},{"group":"E46_SectionDefinition","name":"e46_long_gallery_north"},{"group":"E44_PlaceAppellation","name":"e44_great_chamber"},{"group":"E46_SectionDefinition","name":"e46_long_gallery_west"},{"group":"E82_ActorAppellation","name":"e82_george_henry_law"},{"group":"E62_String","name":"e62_059"},{"group":"E62_String","name":"e62_058"},{"group":"E52_TimeSpan","name":"e52_1946"},{"group":"E62_String","name":"e62_057"},{"group":"E12_Production","name":"e12_porch"},{"group":"E62_String","name":"e62_056"},{"group":"E62_String","name":"e62_055"},{"group":"E62_String","name":"e62_054"},{"group":"E62_String","name":"e62_053"},{"group":"E52_TimeSpan","name":"e52_1450"},{"group":"E07_Activity","name":"e07_painting_portrait_bagot"},{"group":"E44_PlaceAppellation","name":"e44_cathedral_of_st_andrew"},{"group":"E44_PlaceAppellation","name":"e44_bishops_palace"},{"group":"E53_Place","name":"e53_phelps_garden"},{"group":"E62_String","name":"e62_051"},{"group":"E62_String","name":"e62_052"},{"group":"E62_String","name":"e62_050"},{"group":"E62_String","name":"tour\/e62_010"},{"group":"E85_Joining","name":"e85_beckynton"},{"group":"E52_TimeSpan","name":"e52_1975"},{"group":"E62_String","name":"e62_020"},{"group":"E62_String","name":"e62_023"},{"group":"E62_String","name":"tour\/e62_018"},{"group":"E62_String","name":"e62_025"},{"group":"E62_String","name":"e62_024"},{"group":"E62_String","name":"e62_027"},{"group":"E62_String","name":"e62_026"},{"group":"E62_String","name":"e62_029"},{"group":"E62_String","name":"e62_028"},{"group":"E22_ManMadeObject","name":"e22_portrait_bishop_bagot"},{"group":"E52_TimeSpan","name":"e52_1443"},{"group":"E53_Place","name":"e53_outer_gardens"},{"group":"E62_String","name":"e62_xxx"},{"group":"E62_String","name":"tour\/e62_021"},{"group":"E62_String","name":"tour\/e62_022"},{"group":"E21_Person","name":"e21_hervey_arthur"},{"group":"E22_ManMadeObject","name":"e22_portrait_bishop_law"},{"group":"E62_String","name":"e62_031"},{"group":"E42_Identifier","name":"\/data.bishopspalace.org.uk\/portrait_bishop_bagot_01"},{"group":"E42_Identifier","name":"\/data.bishopspalace.org.uk\/long_gallery"},{"group":"E53_Place","name":"e53_east_gallery"},{"group":"E22_ManMadeObject","name":"e22_mache_mouldings"},{"group":"E44_PlaceAppellation","name":"e44_east_gallery"},{"group":"E62_String","name":"tour\/e62_032"},{"group":"E62_String","name":"tour\/e62_033"},{"group":"E62_String","name":"tour\/e62_036"},{"group":"E62_String","name":"e62_030"},{"group":"E62_String","name":"tour\/e62_034"},{"group":"E62_String","name":"tour\/e62_035"},{"group":"E52_TimeSpan","name":"e52_1206"},{"group":"E22_ManMadeObject","name":"e22_chapel"},{"group":"E62_String","name":"e62_100"},{"group":"E55_Type","name":"e55_notes_demo"},{"group":"E62_String","name":"e62_103"},{"group":"E62_String","name":"e62_008"},{"group":"E62_String","name":"e62_104"},{"group":"E62_String","name":"e62_009"},{"group":"E62_String","name":"e62_006"},{"group":"E62_String","name":"e62_101"},{"group":"E62_String","name":"e62_007"},{"group":"E62_String","name":"e62_102"},{"group":"E62_String","name":"e62_107"},{"group":"E62_String","name":"e62_004"},{"group":"E62_String","name":"e62_108"},{"group":"E62_String","name":"e62_005"},{"group":"E62_String","name":"e62_105"},{"group":"E62_String","name":"e62_002"},{"group":"E62_String","name":"e62_106"},{"group":"E62_String","name":"e62_003"},{"group":"E62_String","name":"e62_001"},{"group":"E62_String","name":"e62_109"},{"group":"E41_Appellation","name":"e41_portrait_bishop_bagot"},{"group":"E12_Production","name":"e12_jocelins_palace"},{"group":"E22_ManMadeObject","name":"e22_glastonbury_chair"},{"group":"E85_Joining","name":"e85_jocelin"},{"group":"E41_Appellation","name":"e41_jocelins_palace"},{"group":"E62_String","name":"e62_110"},{"group":"E74_Group","name":"e74_bishop_bath"},{"group":"E62_String","name":"e62_111"},{"group":"E62_String","name":"e62_112"},{"group":"E61_TimePrimitive","name":"e61_1845-1854"},{"group":"E62_String","name":"e62_017"},{"group":"E53_Place","name":"e53_allotments"},{"group":"E62_String","name":"e62_019"},{"group":"E62_String","name":"e62_013"},{"group":"E62_String","name":"e62_014"},{"group":"E62_String","name":"e62_015"},{"group":"E62_String","name":"e62_016"},{"group":"E44_PlaceAppellation","name":"e44_staircase"},{"group":"E62_String","name":"e62_011"},{"group":"E62_String","name":"e62_012"},{"group":"E86_Leaving","name":"e86_piers"},{"group":"E42_Identifier","name":"\/data.bishopspalace.org.uk\/great_hall"},{"group":"E73_InformationObject","name":"\/data.bishopspalace.org.uk\/bishop_bagot.html"},{"group":"E22_ManMadeObject","name":"e22_conference_room"},{"group":"E53_Place","name":"e53_aboretum"},{"group":"E42_Identifier","name":"\/data.bishopspalace.org.uk\/drawing_room"},{"group":"E73_InformationObject","name":"\/data.bishopspalace.org.uk\/croquet_lawn_east.html"},{"group":"E78_Collection","name":"e78_portraits"},{"group":"E22_ManMadeObject","name":"e22_long_gallery_wallpaper"},{"group":"E44_PlaceAppellation","name":"e44_well_pool"},{"group":"E52_TimeSpan","name":"e52_1200"},{"group":"E22_ManMadeObject","name":"e22_entrance_hall_jocelin"},{"group":"E67_Birth","name":"e67_birth_thomas_beckynton"},{"group":"E73_InformationObject","name":"\/data.bishopspalace.org.uk\/welcome.html"},{"group":"E44_PlaceAppellation","name":"e44_victorian_garden"},{"group":"E85_Joining","name":"e85_piers"},{"group":"E73_InformationObject","name":"\/data.bishopspalace.org.uk\/conference_room.html"},{"group":"E53_Place","name":"e53_bishops_chapel"},{"group":"E22_ManMadeObject","name":"e22_portrait_bishop_price"},{"group":"E53_Place","name":"e53_porch_jocelin"},{"group":"E42_Identifier","name":"\/data.bishopspalace.org.uk\/coronation_cope"},{"group":"E12_Production","name":"e12_bishops_chapel"},{"group":"E42_Identifier","name":"\/data.bishopspalace.org.uk\/beckynton_range"},{"group":"E73_InformationObject","name":"\/data.bishopspalace.org.uk\/long_gallery.html"},{"group":"E21_Person","name":"e21_george_henry_law"},{"group":"E42_Identifier","name":"\/data.bishopspalace.org.uk\/bishops_chapel"},{"group":"E53_Place","name":"e53_conference_room"},{"group":"E53_Place","name":"e53_drawing_room"},{"group":"E38_Image","name":"e38_portrait_bishop_price_01"},{"group":"E73_InformationObject","name":"\/data.bishopspalace.org.uk\/east_gallery.html"},{"group":"E55_Type","name":"e55_role_builder"},{"group":"E82_ActorAppellation","name":"e82_hervey_arthur"},{"group":"E82_ActorAppellation","name":"e82_king_edward_sixth"},{"group":"E73_InformationObject","name":"\/data.bishopspalace.org.uk\/croquet_lawn_west.html"},{"group":"E44_PlaceAppellation","name":"e44_allotments"},{"group":"E44_PlaceAppellation","name":"e44_entrance_porch"},{"group":"E81_Transformation","name":"e81_jocelins_palace_remodel"},{"group":"E53_Place","name":"e53_deer_park"},{"group":"E53_Place","name":"e53_market_place_water_fountain"},{"group":"E63_BeginningOfExistence","name":"e63_great_hall"},{"group":"E52_TimeSpan","name":"e52_1239"},{"group":"E25_ManMadeFeature","name":"e25_croquet_lawn"},{"group":"E52_TimeSpan","name":"e52_1242"},{"group":"E82_ActorAppellation","name":"e82_ralph_of_shrewsbury"},{"group":"E81_Transformation","name":"e81_long_gallery_remodel"},{"group":"E21_Person","name":"e21_king_henry_third"},{"group":"E53_Place","name":"e53_long_gallery_west"}]}